password_magic/__init__.py
password_magic/password_utils.py
password_magic-0.1.0.dist-info/METADATA
password_magic-0.1.0.dist-info/WHEEL
password_magic-0.1.0.dist-info/top_level.txt
password_magic-0.1.0.dist-info/RECORD
